scingestor/__init__.py
scingestor/beamtimeWatcher.py
scingestor/configuration.py
scingestor/datasetIngest.py
scingestor/datasetIngestor.py
scingestor/datasetWatcher.py
scingestor/logger.py
scingestor/modelIngest.py
scingestor/pathConverter.py
scingestor/safeINotifier.py
scingestor/scanDirWatcher.py
scingestor-0.20.0.data/data/share/scingestor/default_template.yaml
scingestor-0.20.0.data/data/share/scingestor/format_default.sh
scingestor-0.20.0.data/data/share/scingestor/scingestor.service
scingestor-0.20.0.data/scripts/scicat_dataset_ingest
scingestor-0.20.0.data/scripts/scicat_dataset_ingestor
scingestor-0.20.0.data/scripts/scicat_ingest
scingestor-0.20.0.dist-info/METADATA
scingestor-0.20.0.dist-info/WHEEL
scingestor-0.20.0.dist-info/top_level.txt
scingestor-0.20.0.dist-info/RECORD
