Metadata-Version: 2.1
Name: scingestor
Version: 0.20.0
Summary: Scientific Catalog Tools
Home-page: http://github.com/jkotan/scingestor
Author: ('Jan Kotanski',)
Author-email: jankotan@gmail.com
Maintainer: Jan Kotanski
Maintainer-email: jankotan@gmail.com
License: GNU GENERAL PUBLIC LICENSE, version 3
Keywords: metadata catalog tools metadata photon science
Platform: Linux
Classifier: Development Status :: 5 - Production/Stable
Classifier: Intended Audience :: Science/Research
Classifier: Topic :: Scientific/Engineering :: Physics
Classifier: Topic :: Software Development :: Libraries :: Python Modules
Classifier: License :: OSI Approved :: GNU General Public License v3 (GPLv3)
Classifier: Programming Language :: Python :: 3
Classifier: Programming Language :: Python :: 3.7
Classifier: Programming Language :: Python :: 3.8
Classifier: Programming Language :: Python :: 3.9
Classifier: Programming Language :: Python :: 3.10
Classifier: Programming Language :: Python :: 3.11
Classifier: Programming Language :: Python :: 3.12
Classifier: Programming Language :: Python :: 3.13
Requires-Dist: argcomplete
Requires-Dist: h5py
Requires-Dist: nxstools (>=3.56.0)
Requires-Dist: pyyaml
Requires-Dist: requests
